{
  "day_num": 58,
  "trading_date": "2026-03-10",
  "total_events": 23,
  "event_summary": {
    "EventType.CYCLE_STARTED": 1,
    "EventType.DISTORTION_DETECTED": 1,
    "EventType.MARKET_DATA_READY": 1,
    "EventType.MARKET_REGIME_CLASSIFIED": 1,
    "EventType.REGIME_PROBABILITY_COMPUTED": 1,
    "EventType.META_LEARNING_APPLIED": 1,
    "EventType.EQUITY_SIGNAL_FOUND": 9,
    "EventType.SCAN_COMPLETE": 1,
    "EventType.STRATEGY_LAB_COMPLETE": 1,
    "EventType.RISK_CHECK_PASSED": 1,
    "EventType.SIMULATION_COMPLETE": 1,
    "EventType.TRADE_APPROVED": 1,
    "EventType.CYCLE_COMPLETE": 1,
    "EventType.LEARNING_CYCLE_COMPLETE": 1,
    "EventType.EOD_SELF_EVAL_COMPLETE": 1
  },
  "trace": [
    {
      "ts": "2026-03-12T17:03:21.156049",
      "event_type": "EventType.CYCLE_STARTED",
      "source": "MasterOrchestrator",
      "payload": {
        "ts": "2026-03-12T17:03:21.156046"
      }
    },
    {
      "ts": "2026-03-12T17:03:21.205909",
      "event_type": "EventType.DISTORTION_DETECTED",
      "source": "MarketDistortionScanner",
      "payload": {
        "risk_level": "LOW",
        "stress_score": 0,
        "any_distortion": false,
        "active_flags": [],
        "trading_allowed": true,
        "size_multiplier": 1.0,
        "max_new_trades": 10,
        "hedge_preferred": false,
        "sector_watches": []
      }
    },
    {
      "ts": "2026-03-12T17:03:21.233008",
      "event_type": "EventType.MARKET_DATA_READY",
      "source": "MarketDataAI",
      "payload": {
        "vix": 18.91,
        "regime": "range_market",
        "breadth": 0.62,
        "pcr": 1.1
      }
    },
    {
      "ts": "2026-03-12T17:03:21.298026",
      "event_type": "EventType.MARKET_REGIME_CLASSIFIED",
      "source": "MarketRegimeAI",
      "payload": {
        "regime": "range_market",
        "volatility": "VolatilityLevel.HIGH"
      }
    },
    {
      "ts": "2026-03-12T17:03:21.328767",
      "event_type": "EventType.REGIME_PROBABILITY_COMPUTED",
      "source": "RegimeProbabilityModel",
      "payload": {
        "trend_prob": 0.0498,
        "range_prob": 0.9051,
        "volatile_prob": 0.0369,
        "bear_prob": 0.0082,
        "dominant": "range_market",
        "confidence": 0.8553,
        "stress_adjusted": false,
        "strategy_mix": {
          "momentum": 0.0274,
          "breakout": 0.0224,
          "mean_reversion": 0.9051,
          "hedging": 0.0146,
          "options_spread": 0.0306
        }
      }
    },
    {
      "ts": "2026-03-12T17:03:21.366920",
      "event_type": "EventType.META_LEARNING_APPLIED",
      "source": "MetaLearningEngine",
      "payload": {
        "top_strategy": "Breakout_Volume",
        "model_active": false,
        "allocations": {
          "Breakout_Volume": 0.025,
          "Momentum_Retest": 0.025,
          "Mean_Reversion": 0.025,
          "Bull_Call_Spread": 0.025,
          "Iron_Condor_Range": 0.025,
          "Hedging_Model": 0.025,
          "Short_Straddle_IV_Spike": 0.025,
          "Long_Straddle_Pre_Event": 0.025,
          "Futures_Basis_Arb": 0.025,
          "ETF_NAV_Arb": 0.025,
          "Breakout_Volume_RSI_HiVol": 0.025,
          "Mean_Reversion_RSI_HiVol": 0.025,
          "EDG_COMPOS_92_EE0002": 0.025,
          "EDG_MACRO__78_EE0000": 0.025,
          "EDG_VOLATI_91_EE0004": 0.025,
          "EDG_VOLATI_68_EE0000": 0.025,
          "EDG_VOLATI_63_EE0002": 0.025,
          "EDG_VOLATI_61_EE0001": 0.025,
          "EDG_COMPOS_93_EE0003": 0.025,
          "EDG_COMPOS_82_EE0000": 0.025,
          "EDG_MACRO__72_EE0001": 0.025,
          "EDG_COMPOS_94_EE0003": 0.025,
          "EDG_MACRO__64_EE0001": 0.025,
          "EDG_COMPOS_86_EE0001": 0.025,
          "EDG_VOLATI_93_EE0002": 0.025,
          "EDG_VOLATI_74_EE0000": 0.025,
          "EDG_VOLATI_94_EE0002": 0.025,
          "EDG_VOLATI_75_EE0000": 0.025,
          "EDG_VOLATI_89_EE0002": 0.025,
          "EDG_VOLATI_76_EE0000": 0.025,
          "EDG_VOLATI_77_EE0000": 0.025,
          "EDG_VOLATI_90_EE0002": 0.025,
          "EDG_VOLATI_78_EE0000": 0.025,
          "EDG_VOLATI_79_EE0000": 0.025,
          "EDG_VOLATI_80_EE0000": 0.025,
          "EDG_VOLATI_91_EE0002": 0.025,
          "EDG_VOLATI_81_EE0000": 0.025,
          "EDG_VOLATI_91_EE0003": 0.025,
          "EDG_VOLATI_82_EE0000": 0.025,
          "EDG_VOLATI_92_EE0003": 0.025
        }
      }
    },
    {
      "ts": "2026-03-12T17:03:21.397306",
      "event_type": "EventType.EQUITY_SIGNAL_FOUND",
      "source": "EquityScannerAI",
      "payload": {
        "symbol": "BAJFINANCE",
        "direction": "SignalDirection.BUY",
        "strategy": "Mean_Reversion",
        "confidence": 6.83
      }
    },
    {
      "ts": "2026-03-12T17:03:21.402887",
      "event_type": "EventType.EQUITY_SIGNAL_FOUND",
      "source": "EquityScannerAI",
      "payload": {
        "symbol": "SUNPHARMA",
        "direction": "SignalDirection.SHORT",
        "strategy": "Mean_Reversion",
        "confidence": 8.5
      }
    },
    {
      "ts": "2026-03-12T17:03:21.407538",
      "event_type": "EventType.EQUITY_SIGNAL_FOUND",
      "source": "EquityScannerAI",
      "payload": {
        "symbol": "DRREDDY",
        "direction": "SignalDirection.BUY",
        "strategy": "Momentum_Retest",
        "confidence": 6.5
      }
    },
    {
      "ts": "2026-03-12T17:03:21.442471",
      "event_type": "EventType.EQUITY_SIGNAL_FOUND",
      "source": "EquityScannerAI",
      "payload": {
        "symbol": "NIFTY",
        "direction": "SignalDirection.SELL",
        "strategy": "Short_Straddle_IV_Spike",
        "confidence": 7.642857142857142
      }
    },
    {
      "ts": "2026-03-12T17:03:21.471877",
      "event_type": "EventType.EQUITY_SIGNAL_FOUND",
      "source": "EquityScannerAI",
      "payload": {
        "symbol": "BANKNIFTY",
        "direction": "SignalDirection.SELL",
        "strategy": "Short_Straddle_IV_Spike",
        "confidence": 7.75
      }
    },
    {
      "ts": "2026-03-12T17:03:21.482587",
      "event_type": "EventType.EQUITY_SIGNAL_FOUND",
      "source": "EquityScannerAI",
      "payload": {
        "symbol": "NIFTY",
        "direction": "SignalDirection.SHORT",
        "strategy": "Futures_Basis_Arb",
        "confidence": 8.0
      }
    },
    {
      "ts": "2026-03-12T17:03:21.497248",
      "event_type": "EventType.EQUITY_SIGNAL_FOUND",
      "source": "EquityScannerAI",
      "payload": {
        "symbol": "BANKNIFTY",
        "direction": "SignalDirection.SHORT",
        "strategy": "Futures_Basis_Arb",
        "confidence": 8.0
      }
    },
    {
      "ts": "2026-03-12T17:03:21.533917",
      "event_type": "EventType.EQUITY_SIGNAL_FOUND",
      "source": "EquityScannerAI",
      "payload": {
        "symbol": "NIFTYBEES",
        "direction": "SignalDirection.BUY",
        "strategy": "ETF_NAV_Arb",
        "confidence": 7.5
      }
    },
    {
      "ts": "2026-03-12T17:03:21.555601",
      "event_type": "EventType.EQUITY_SIGNAL_FOUND",
      "source": "EquityScannerAI",
      "payload": {
        "symbol": "BANKBEES",
        "direction": "SignalDirection.SELL",
        "strategy": "ETF_NAV_Arb",
        "confidence": 7.5
      }
    },
    {
      "ts": "2026-03-12T17:03:21.562109",
      "event_type": "EventType.SCAN_COMPLETE",
      "source": "MasterOrchestrator",
      "payload": {
        "equity": 3,
        "options": 2,
        "arb": 4,
        "total": 9
      }
    },
    {
      "ts": "2026-03-12T17:03:21.573518",
      "event_type": "EventType.STRATEGY_LAB_COMPLETE",
      "source": "StrategyGeneratorAI",
      "payload": {
        "assigned": 2,
        "after_evo": 2,
        "after_bt": 1
      }
    },
    {
      "ts": "2026-03-12T17:03:21.633215",
      "event_type": "EventType.RISK_CHECK_PASSED",
      "source": "RiskManagerAI",
      "payload": {
        "approved": 1
      }
    },
    {
      "ts": "2026-03-12T17:03:21.701204",
      "event_type": "EventType.SIMULATION_COMPLETE",
      "source": "SimulationEngine",
      "payload": {
        "approved": 1,
        "rejected": 0,
        "rate": 1.0
      }
    },
    {
      "ts": "2026-03-12T17:03:21.766904",
      "event_type": "EventType.TRADE_APPROVED",
      "source": "DecisionEngine",
      "payload": {
        "symbol": "SUNPHARMA",
        "strategy": "Mean_Reversion_RSI_HiVol",
        "score": 6.62,
        "modifier": 0.794,
        "votes": {}
      }
    },
    {
      "ts": "2026-03-12T17:03:21.831454",
      "event_type": "EventType.CYCLE_COMPLETE",
      "source": "MasterOrchestrator",
      "payload": {
        "signals_processed": 1
      }
    },
    {
      "ts": "2026-03-12T17:03:21.899612",
      "event_type": "EventType.LEARNING_CYCLE_COMPLETE",
      "source": "LearningEngine",
      "payload": {
        "trades_processed": 0
      }
    },
    {
      "ts": "2026-03-12T17:03:22.282960",
      "event_type": "EventType.EOD_SELF_EVAL_COMPLETE",
      "source": "DailyAISelfEvaluator",
      "payload": {
        "overall_score": 0.0,
        "grade": "N/A",
        "issues_count": 0
      }
    }
  ]
}